gradle.properties
hexdoc_hexdim/__gradle_version__.py
hexdoc_hexdim/__init__.py
hexdoc_hexdim/__version__.py
hexdoc_hexdim/_hooks.py
hexdoc_hexdim/py.typed
hexdoc_hexdim/_export/.gitignore
hexdoc_hexdim/_export/__init__.py
hexdoc_hexdim/_export/generated/__init__.py
hexdoc_hexdim/_export/generated/hexdim.hexdoc.json
hexdoc_hexdim/_export/generated/hexdim.patterns.hexdoc.json
hexdoc_hexdim/_export/generated/assets/hexcasting/lang/en_us.flatten.json5
hexdoc_hexdim/_export/generated/assets/hexcasting/patchouli_books/thehexbook/en_us/entries/patterns/great_spells/dimension.json
hexdoc_hexdim/_export/generated/assets/hexdim/lang/en_us.json
hexdoc_hexdim/_export/generated/assets/hexdim/lang/zh_cn.json
hexdoc_hexdim/_export/generated/data/hexcasting/tags/action/per_world_pattern.json
hexdoc_hexdim/_templates/__init__.py
hexdoc_hexdim-1.2.1.1.20.0.dist-info/METADATA
hexdoc_hexdim-1.2.1.1.20.0.dist-info/WHEEL
hexdoc_hexdim-1.2.1.1.20.0.dist-info/entry_points.txt
hexdoc_hexdim-1.2.1.1.20.0.dist-info/licenses/LICENSE
hexdoc_hexdim-1.2.1.1.20.0.dist-info/RECORD
