Metadata-Version: 2.1
Name: hexdoc-hexdim
Version: 1.2.1.1.20.0
Summary: Python web book docgen and hexdoc plugin for Hexxy Dimensions.
Project-URL: Homepage, https://walksanatora.github.io/hexxy-dimensions/
Project-URL: Source, https://github.com/walksanatora/hexxy-dimensions
Author: walksanatora
License-File: LICENSE
Keywords: hexdoc
Requires-Python: >=3.11
Requires-Dist: hexdoc-hexcasting~=0.11.1.1.0rc7.dev20
Provides-Extra: dev
Requires-Dist: ruff~=0.1.4; extra == 'dev'
